{
  "name": "m4a4",
  "description": "M4A4 recoil pattern",
  "defaultHotkey": 0,
  "baseSettings": {
    "sensitivity": 2.0,
    "resolution": {
      "width": 1920,
      "height": 1080
    },
    "aspectRatio": "16:9"
  },
  "pattern": [
    {"x": 0, "y": 0, "d": 1},
    {"x": 0, "y": 0, "d": 1},
    {"x": 0, "y": 0, "d": 2},
    {"x": 0, "y": 0, "d": 2},
    {"x": 0, "y": 0, "d": 2},
    {"x": 0, "y": 0, "d": 2},
    {"x": 0, "y": 0, "d": 2},
    {"x": 0, "y": 0, "d": 2},
    {"x": 0, "y": 0, "d": 2},
    {"x": 0, "y": 0, "d": 2},
    {"x": 0, "y": 0, "d": 2},
    {"x": 0, "y": 0, "d": 2},
    {"x": 0, "y": 0, "d": 7},
    {"x": 0, "y": 0, "d": 7},
    {"x": 0, "y": 0, "d": 7},
    {"x": 0, "y": 0, "d": 7},
    {"x": 0, "y": 0, "d": 7},
    {"x": 0, "y": 0, "d": 7},
    {"x": 0, "y": 0, "d": 7},
    {"x": 0, "y": 0, "d": 7},
    {"x": 0, "y": 0, "d": 8},
    {"x": 0, "y": 0, "d": 8},
    {"x": 0, "y": 0, "d": 8},
    {"x": 0, "y": 0, "d": 8},
    {"x": -1, "y": 2, "d": 7},
    {"x": -1, "y": 2, "d": 7},
    {"x": -1, "y": 1, "d": 7},
    {"x": -1, "y": 1, "d": 7},
    {"x": 0, "y": 1, "d": 7},
    {"x": 0, "y": 1, "d": 7},
    {"x": 0, "y": 1, "d": 7},
    {"x": 0, "y": 1, "d": 8},
    {"x": 0, "y": 1, "d": 8},
    {"x": 0, "y": 1, "d": 8},
    {"x": 0, "y": 1, "d": 8},
    {"x": 0, "y": 1, "d": 8}
  ]
}